mongodump_s3/__init__.py
mongodump_s3/__main__.py
mongodump_s3/dump.py
mongodump_s3/helpers.py
mongodump_s3/notifications.py
mongodump_s3/s3.py
mongodump_s3-1.1.2.dist-info/LICENSE
mongodump_s3-1.1.2.dist-info/METADATA
mongodump_s3-1.1.2.dist-info/WHEEL
mongodump_s3-1.1.2.dist-info/entry_points.txt
mongodump_s3-1.1.2.dist-info/top_level.txt
mongodump_s3-1.1.2.dist-info/RECORD
