Metadata-Version: 2.1
Name: mongodump-s3
Version: 1.1.2
Summary: Backup utility for MongoDB. Compatible with Azure, Amazon Web Services and Google Cloud Platform.
Home-page: https://github.com/exesse/mongodump-s3
Author: Vladislav I. Kulbatski 
Author-email: hi@exesse.org
License: MIT
Platform: UNKNOWN
Classifier: License :: OSI Approved :: MIT License
Classifier: Programming Language :: Python :: 3
Classifier: Programming Language :: Python :: 3.8
License-File: LICENSE
Requires-Dist: requests (>=2.26.0)
Requires-Dist: hurry.filesize (==0.9)
Requires-Dist: python-dotenv (>=0.18.0)
Requires-Dist: azure-storage-blob (>=12.8.1)
Requires-Dist: boto3 (>=1.17.111)
Requires-Dist: google-cloud-storage (>=1.41.0)
